spsdk_pyocd/__init__.py
spsdk_pyocd/probe.py
spsdk_pyocd/__pyinstaller/__init__.py
spsdk_pyocd/__pyinstaller/hook-spsdk_pyocd.py
spsdk_pyocd-0.3.0.dist-info/LICENSE
spsdk_pyocd-0.3.0.dist-info/METADATA
spsdk_pyocd-0.3.0.dist-info/WHEEL
spsdk_pyocd-0.3.0.dist-info/entry_points.txt
spsdk_pyocd-0.3.0.dist-info/top_level.txt
spsdk_pyocd-0.3.0.dist-info/RECORD
