Metadata-Version: 2.1
Name: spsdk-pyocd
Version: 0.3.0
Summary: PyOCD SW Debugger. A debugger probe plugin for SPSDK.
Author: NXP
Maintainer-email: NXP <michal.starecek@nxp.com>
License: BSD-3-Clause
Project-URL: Homepage, https://github.com/nxp-mcuxpresso/spsdk_plugins/tree/master/pemicro
Project-URL: Issues, https://github.com/nxp-mcuxpresso/spsdk_plugins/issues
Keywords: NXP,SPSDK,pyocd
Classifier: Development Status :: 2 - Pre-Alpha
Classifier: Intended Audience :: Developers
Classifier: License :: OSI Approved :: BSD License
Classifier: Natural Language :: English
Classifier: Programming Language :: Python :: 3
Classifier: Programming Language :: Python :: 3.9
Classifier: Programming Language :: Python :: 3.10
Classifier: Programming Language :: Python :: 3.11
Classifier: Programming Language :: Python :: 3.12
Requires-Python: >=3.9
License-File: LICENSE
Requires-Dist: pyocd<0.37,>=0.35.1
Provides-Extra: pemicro
Requires-Dist: pyocd-pemicro<1.2,>=1.1.5; extra == "pemicro"
